{
  "game_mode": 3,
  "account_code": 2,
  "first_role": 34,
  "last_role": 37,
  "skip_role_enabled": false,
  "skip_role_list": "5,16",
  "stronger_uniform": false,
  "stronger_fatigue": 180,
  "buy_tank": 0,
  "buy_bell": 0,
  "buy_ssm": 2,
  "buy_catalyst": 7,
  "abyss_account_code": 1,
  "abyss_first": 5,
  "abyss_last": 5,
  "abyss_skip_role_enabled": false,
  "abyss_skip_role_list": "",
  "abyss_uniform": false,
  "abyss_fatigue": 18,
  "abyss_tank": 0,
  "abyss_bell": 0,
  "abyss_ssm": 2,
  "abyss_catalyst": 7,
  "enable_pic_log": true,
  "schedule_hour": 17,
  "schedule_minute": 47,
  "schedule_mode": 1,
  "current_tab": 0
}